pyswitcherio/__init__.py
PySwitcherIO-0.0.7.dist-info/LICENSE
PySwitcherIO-0.0.7.dist-info/METADATA
PySwitcherIO-0.0.7.dist-info/WHEEL
PySwitcherIO-0.0.7.dist-info/top_level.txt
PySwitcherIO-0.0.7.dist-info/RECORD
