Metadata-Version: 2.1
Name: PySwitcherIO
Version: 0.0.7
Summary: IOSwitcher in korea
Home-page: https://github.com/damob-byun/PySwitcherIO
Author: Damob.byun
License: MIT
Classifier: Development Status :: 3 - Alpha
Classifier: Environment :: Other Environment
Classifier: Intended Audience :: Developers
Classifier: Operating System :: OS Independent
Classifier: Programming Language :: Python
Classifier: Topic :: Home Automation
Classifier: Topic :: Software Development :: Libraries :: Python Modules
License-File: LICENSE
Requires-Dist: bleak
